{
  "StartDate": "2023-05-08",
  "NumberOfDays": 7,
  "Data": {
    "Average": 15.666623051790975,
    "DataPoints": [
      {
        "Value": 15.555621400152432,
        "Date": "2023-05-10T18:19:53.47Z"
      },
      {
        "Value": 16.666654321033377,
        "Date": "2023-05-08T08:12:40.314Z"
      },
      {
        "Value": 16.666650205822283,
        "Date": "2023-05-10T00:13:03.985Z"
      },
      {
        "Value": 15.555279845190933,
        "Date": "2023-05-09T18:02:31.254Z"
      },
      {
        "Value": 16.66643622594055,
        "Date": "2023-05-08T00:12:46.133Z"
      },
      {
        "Value": 13.333222225194241,
        "Date": "2023-05-10T08:12:51.889Z"
      },
      {
        "Value": 15.555452676284085,
        "Date": "2023-05-08T18:32:10.663Z"
      },
      {
        "Value": 14.44425514866625,
        "Date": "2023-05-09T08:14:06.428Z"
      },
      {
        "Value": 16.66717698649807,
        "Date": "2023-05-11T00:12:47.932Z"
      },
      {
        "Value": 15.555481483127537,
        "Date": "2023-05-09T00:13:15.8Z"
      }
    ]
  }
}
