{
  "StartDate": "2023-05-08",
  "NumberOfDays": 7,
  "Data": {
    "Average": 23.00766893592369,
    "DataPoints": [
      {
        "Value": 28.954545454545453,
        "Date": "2023-05-10T18:19:53.47Z"
      },
      {
        "Value": 19.682692307692307,
        "Date": "2023-05-08T08:12:40.314Z"
      },
      {
        "Value": 28.958333333333332,
        "Date": "2023-05-10T00:13:03.985Z"
      },
      {
        "Value": 19.5,
        "Date": "2023-05-09T18:02:31.254Z"
      },
      {
        "Value": 19.5,
        "Date": "2023-05-08T00:12:46.133Z"
      },
      {
        "Value": 19.952380952380953,
        "Date": "2023-05-10T08:12:51.889Z"
      },
      {
        "Value": 26.428571428571423,
        "Date": "2023-05-08T18:32:10.663Z"
      },
      {
        "Value": 27.441176470588232,
        "Date": "2023-05-09T08:14:06.428Z"
      },
      {
        "Value": 19.78136642238008,
        "Date": "2023-05-11T00:12:47.932Z"
      },
      {
        "Value": 19.877622989745145,
        "Date": "2023-05-09T00:13:15.8Z"
      }
    ]
  }
}
